helix_mockserver_client-2.0.7.dist-info/licenses/LICENSE
mockserver_client/__init__.py
mockserver_client/_time.py
mockserver_client/_timing.py
mockserver_client/error_messages.py
mockserver_client/match_request_result.py
mockserver_client/mock_expectation.py
mockserver_client/mock_request.py
mockserver_client/mock_request_logger.py
mockserver_client/mock_request_response.py
mockserver_client/mock_requests_loader.py
mockserver_client/mock_response.py
mockserver_client/mockserver_client.py
mockserver_client/mockserver_verify_exception.py
mockserver_client/py.typed
mockserver_client/exceptions/__init__.py
mockserver_client/exceptions/mock_server_exception.py
mockserver_client/exceptions/mock_server_expectation_not_found_exception.py
mockserver_client/exceptions/mock_server_json_content_mismatch_exception.py
mockserver_client/exceptions/mock_server_request_not_found_exception.py
tests/__init__.py
tests/test_chunk_transfer.py
tests/test_chunk_transfer_using_aiohttp.py
tests/from_file/__init__.py
tests/from_file/test_mock_server_from_file.py
tests/from_file_content_chunk_transfer/__init__.py
tests/from_file_content_chunk_transfer/test_mock_server_content_chunk_transfer.py
tests/from_file_content_type_form_urlencoded/__init__.py
tests/from_file_content_type_form_urlencoded/test_mock_server_content_type_url_formencoded.py
tests/from_file_multiple_calls/__init__.py
tests/from_file_multiple_calls/test_mock_server_from_file_multiple_calls.py
tests/from_file_multiple_calls_mismatch/__init__.py
tests/from_file_multiple_calls_mismatch/test_mock_server_from_file_multiple_calls_mismatch.py
tests/from_file_multiple_calls_missing_expectation/__init__.py
tests/from_file_multiple_calls_missing_expectation/test_mock_server_from_file_multiple_calls_missing_expectation.py
tests/from_file_multiple_calls_missing_request/__init__.py
tests/from_file_multiple_calls_missing_request/test_mock_server_from_file_multiple_calls_missing_request.py
tests/ignore_timestamp_field/__init__.py
tests/ignore_timestamp_field/test_mock_server_ignore_timestamp.py
helix_mockserver_client-2.0.7.dist-info/METADATA
helix_mockserver_client-2.0.7.dist-info/WHEEL
helix_mockserver_client-2.0.7.dist-info/top_level.txt
helix_mockserver_client-2.0.7.dist-info/RECORD
