Metadata-Version: 2.4
Name: helix_mockserver_client
Version: 2.0.7
Summary: mockserver_client
Home-page: https://github.com/icanbwell/mockserver_client
Author: Imran Qureshi
Author-email: imran.qureshi@icanbwell.com
Classifier: Development Status :: 4 - Beta
Classifier: Programming Language :: Python :: 3
Classifier: License :: OSI Approved :: Apache Software License
Classifier: Operating System :: OS Independent
Requires-Python: >=3.12
License-File: LICENSE
Requires-Dist: requests
Requires-Dist: deepdiff
Dynamic: author
Dynamic: author-email
Dynamic: classifier
Dynamic: description
Dynamic: description-content-type
Dynamic: home-page
Dynamic: license-file
Dynamic: requires-dist
Dynamic: requires-python
Dynamic: summary
